{
  "name": "t:sections.footer.name",
  "type": "footer",
  "sections": {
    "footer": {
      "type": "footer",
      "blocks": {
        "footer-0": {
          "type": "link_list",
          "settings": {
            "heading": "Work with us",
            "menu": "main-menu"
          }
        },
        "footer-2": {
          "type": "text",
          "settings": {
            "heading": "Lucid",
            "subtext": "<p>Founded in 2000, we have been working with Shopify since 2006—and are one of the original 12 agencies invited into the Shopify Partners program.<\/p>"
          }
        }
      },
      "block_order": [
        "footer-0",
        "footer-2"
      ],
      "settings": {
        "color_scheme": "background-2",
        "newsletter_enable": false,
        "newsletter_heading": "Stay in the loop with Lucid",
        "enable_follow_on_shop": false,
        "show_social": false,
        "enable_country_selector": false,
        "enable_language_selector": false,
        "payment_enable": true,
        "show_policy": false,
        "margin_top": 40,
        "padding_top": 40,
        "padding_bottom": 40
      }
    }
  },
  "order": [
    "footer"
  ]
}
